alibabacloud_mse20190531/__init__.py
alibabacloud_mse20190531/client.py
alibabacloud_mse20190531/models/__init__.py
alibabacloud_mse20190531/models/_add_auth_policy_request.py
alibabacloud_mse20190531/models/_add_auth_policy_response.py
alibabacloud_mse20190531/models/_add_auth_policy_response_body.py
alibabacloud_mse20190531/models/_add_auth_resource_request.py
alibabacloud_mse20190531/models/_add_auth_resource_response.py
alibabacloud_mse20190531/models/_add_auth_resource_response_body.py
alibabacloud_mse20190531/models/_add_auth_resource_shrink_request.py
alibabacloud_mse20190531/models/_add_black_white_list_request.py
alibabacloud_mse20190531/models/_add_black_white_list_response.py
alibabacloud_mse20190531/models/_add_black_white_list_response_body.py
alibabacloud_mse20190531/models/_add_gateway_auth_consumer_request.py
alibabacloud_mse20190531/models/_add_gateway_auth_consumer_response.py
alibabacloud_mse20190531/models/_add_gateway_auth_consumer_response_body.py
alibabacloud_mse20190531/models/_add_gateway_auth_request.py
alibabacloud_mse20190531/models/_add_gateway_auth_response.py
alibabacloud_mse20190531/models/_add_gateway_auth_response_body.py
alibabacloud_mse20190531/models/_add_gateway_auth_shrink_request.py
alibabacloud_mse20190531/models/_add_gateway_domain_request.py
alibabacloud_mse20190531/models/_add_gateway_domain_response.py
alibabacloud_mse20190531/models/_add_gateway_domain_response_body.py
alibabacloud_mse20190531/models/_add_gateway_domain_shrink_request.py
alibabacloud_mse20190531/models/_add_gateway_request.py
alibabacloud_mse20190531/models/_add_gateway_response.py
alibabacloud_mse20190531/models/_add_gateway_response_body.py
alibabacloud_mse20190531/models/_add_gateway_route_request.py
alibabacloud_mse20190531/models/_add_gateway_route_response.py
alibabacloud_mse20190531/models/_add_gateway_route_response_body.py
alibabacloud_mse20190531/models/_add_gateway_route_shrink_request.py
alibabacloud_mse20190531-6.23.1.dist-info/LICENSE
alibabacloud_mse20190531-6.23.1.dist-info/METADATA
alibabacloud_mse20190531-6.23.1.dist-info/WHEEL
alibabacloud_mse20190531-6.23.1.dist-info/top_level.txt
alibabacloud_mse20190531-6.23.1.dist-info/RECORD
